annotile/__init__.py
annotile/dataloader/__init__.py
annotile/dataloader/dataloader.py
annotile/image_tiler/__init__.py
annotile/image_tiler/image_tiler.py
annotile/label_tiler/__init__.py
annotile/label_tiler/label_tiler.py
annotile/main.py
annotile-0.0.1.dist-info/LICENSE
annotile-0.0.1.dist-info/METADATA
annotile-0.0.1.dist-info/WHEEL
annotile-0.0.1.dist-info/RECORD
